a4/__init__.py
a4/a4.py
a4-0.4.dist-info/LICENSE
a4-0.4.dist-info/METADATA
a4-0.4.dist-info/WHEEL
a4-0.4.dist-info/top_level.txt
a4-0.4.dist-info/RECORD
