Metadata-Version: 2.1
Name: a4
Version: 0.4
Summary: A Python package for terminal utilities and screenshot capturing.
Author: BL1Z33
Classifier: Programming Language :: Python :: 3
Classifier: License :: OSI Approved :: MIT License
Classifier: Operating System :: Microsoft :: Windows
License-File: LICENSE
Requires-Dist: Pillow
